tkwin11fpsmon/__init__.py
tkwin11fpsmon/__main__.py
tkwin11fpsmon-0.1.0.dist-info/METADATA
tkwin11fpsmon-0.1.0.dist-info/WHEEL
tkwin11fpsmon-0.1.0.dist-info/entry_points.txt
tkwin11fpsmon-0.1.0.dist-info/top_level.txt
tkwin11fpsmon-0.1.0.dist-info/RECORD
