Metadata-Version: 2.4
Name: tkwin11fpsmon
Version: 0.1.0
Summary: Lightweight FPS overlay for Windows 11 using tkinter and DWM flush
Author-email: Amanokawa Kaede <73207881+KAEDEAK@users.noreply.github.com>
License: MIT
Project-URL: Homepage, https://github.com/KAEDEAK/tkwin11fpsmon
Requires-Python: >=3.8
Requires-Dist: pywin32
